{
  "tagline": "Seasonal New American, bar + craft cocktails in the Sierra foothills",
  "heroSubtitle": "A cozy gathering place with fresh flavors & locally inspired spirit.",
  "categoryIntros": {
    "Beginnings": "Shareable bites to begin your culinary journey.",
    "Salads": "Greens, roots & vibrant flavors — made with local produce.",
    "Sandwiches": "Handhelds with personality and choice sides.",
    "Grill & Main": "Steaks, seafood & more — from fire, pan, and heart.",
    "Desserts": "Sweet finales crafted by our pastry chef."
  },
  "specials": "Ask your server for this week’s specials & cocktail pairings."
}
